gif_player/GifPlayer.py
gif_player/__init__.py
gif_player/_imports_.py
gif_player/gif_player.min.css
gif_player/gif_player.min.js
gif_player/gif_player.min.js.map
gif_player/metadata.json
gif_player/package-info.json
gif_player-0.0.5.dist-info/LICENSE
gif_player-0.0.5.dist-info/METADATA
gif_player-0.0.5.dist-info/WHEEL
gif_player-0.0.5.dist-info/top_level.txt
gif_player-0.0.5.dist-info/RECORD
