Metadata-Version: 2.1
Name: gif_player
Version: 0.0.5
Summary: Gif Player for Dash
Author: Gabriel Carvajal <gcarvajal2001@gmail.com>
License: GPL-3.0
Classifier: Framework :: Dash
License-File: LICENSE
